src/__init__.py
src/cli.py
src/converter.py
src/core.py
Dency-2.1.dist-info/METADATA
Dency-2.1.dist-info/WHEEL
Dency-2.1.dist-info/entry_points.txt
Dency-2.1.dist-info/top_level.txt
Dency-2.1.dist-info/RECORD
