Metadata-Version: 2.1
Name: Dency
Version: 2.1
Summary: tool to fetch and generate requirements.txt for Python projects
Home-page: https://github.com/11PRIMUS/Dency
Author: PRIMUS
Author-email: alokpal2803@gmail.com
Classifier: Programming Language :: Python :: 3
Classifier: License :: OSI Approved :: MIT License
Classifier: Operating System :: OS Independent
Requires-Python: >=3.7
Requires-Dist: click
Requires-Dist: requests
Provides-Extra: dev
Requires-Dist: black ; extra == 'dev'
Requires-Dist: pytest ; extra == 'dev'
